django_rest_swagger_docstring/__init__.py
django_rest_swagger_docstring/parsers.py
django_rest_swagger_docstring/schemas.py
django_rest_swagger_docstring/urls.py
django_rest_swagger_docstring/views.py
django_rest_swagger_docstring_ext-0.3.0.dist-info/METADATA
django_rest_swagger_docstring_ext-0.3.0.dist-info/RECORD
django_rest_swagger_docstring_ext-0.3.0.dist-info/WHEEL
django_rest_swagger_docstring_ext-0.3.0.dist-info/top_level.txt
